[
    {
        "Title": "Shop on eBay",
        "Price": "$20.00",
        "Image URL": "https://ir.ebaystatic.com/rs/v/fxxj3ttftm5ltcqnto1o4baovyl.png"
    },
    {
        "Title": "Poor Mans Power Steering 1\" Kit Fits MANY Brands Garden Tractors & Mowers\u00a0PMPS",
        "Price": "$55.00",
        "Image URL": "https://i.ebayimg.com/thumbs/images/g/eigAAOSwPX1j-BYO/s-l225.jpg"
    },
    {
        "Title": "Low Back Lawn Mower Garden Tractor Seat Black",
        "Price": "$74.99",
        "Image URL": "https://i.ebayimg.com/thumbs/images/g/9DkAAOSwbgVfoaGP/s-l225.jpg"
    },
    {
        "Title": "New Plastic Headlight Lens for Vintage Garden Tractors Ford Case, Ingersoll",
        "Price": "$9.95",
        "Image URL": "https://i.ebayimg.com/thumbs/images/g/bn0AAOSwhY5i6Anl/s-l225.jpg"
    },
    {
        "Title": "GENUINE OEM TORO PART #110148 PULLEY FOR 36\", 42\", & 48\" LAWN & GARDEN TRACTORS",
        "Price": "$79.99",
        "Image URL": "https://i.ebayimg.com/thumbs/images/g/2Z0AAOSwVVlcgZ9F/s-l225.jpg"
    },
    {
        "Title": "EXTRA-HEAVY DUTY 7 GAUGE!!!  Mule Drive Cover John Deere 140 316 317 318 322 332",
        "Price": "$54.75",
        "Image URL": "https://i.ebayimg.com/thumbs/images/g/YrAAAOxy86RSWGpi/s-l225.jpg"
    },
    {
        "Title": "Two 13X5.00-6 13/500-6 Smooth Rib 4 Ply Lawn Mower Garden Tractor Tires",
        "Price": "$44.99",
        "Image URL": "https://i.ebayimg.com/thumbs/images/g/abgAAOSwZQxW3zAY/s-l225.jpg"
    },
    {
        "Title": "Sears garden tractor Suburban SS12 ST12 ST16, etc. 3 Point Hitch Rear Lift",
        "Price": "$185.00",
        "Image URL": "https://i.ebayimg.com/thumbs/images/g/pS8AAOSwKTdjzYMy/s-l225.jpg"
    },
    {
        "Title": "JOHN DEERE GARDEN TRACTOR 140 HOOD DECALS SET",
        "Price": "$45.00",
        "Image URL": "https://i.ebayimg.com/thumbs/images/g/944AAOSwxehXOikY/s-l225.jpg"
    },
    {
        "Title": "OIL FILTER fits Kawasaki FB460V FC420V FC540V FD501D FD590V FR651V FR691V FR730V",
        "Price": "$9.99",
        "Image URL": "https://i.ebayimg.com/thumbs/images/g/fckAAOSwqDtjvy8j/s-l225.jpg"
    },
    {
        "Title": "JOHN DEERE GARDEN TRACTOR 400 HOOD DECALS SET",
        "Price": "$45.00",
        "Image URL": "https://i.ebayimg.com/thumbs/images/g/E-wAAOSwi0RXxOgg/s-l225.jpg"
    },
    {
        "Title": "GENUINE OEM TORO PART # 112214 CHOKE CONTROL CABLE FOR GARDEN TRACTORS",
        "Price": "$40.34",
        "Image URL": "https://i.ebayimg.com/thumbs/images/g/R94AAOSwH61cSjeI/s-l225.jpg"
    },
    {
        "Title": "High Back Lawn Mower Garden Tractor Seat Black",
        "Price": "$99.99",
        "Image URL": "https://i.ebayimg.com/thumbs/images/g/9O0AAOSwkEJfobYo/s-l225.jpg"
    },
    {
        "Title": "New ListingNOS John Deere Lawn Sweeper Garden Tractor Starter Brush Kit AM38665",
        "Price": "$25.00",
        "Image URL": "https://i.ebayimg.com/thumbs/images/g/lD8AAOSwxdxkTvcV/s-l225.jpg"
    },
    {
        "Title": "Poor Mans Power Steering 3/4\" Kit Fits MANY Brands Garden Tractors & Mowers\u00a0PMPS",
        "Price": "$53.00",
        "Image URL": "https://i.ebayimg.com/thumbs/images/g/JYIAAOSwCFlj-BiE/s-l225.jpg"
    },
    {
        "Title": "Cub Cadet Fine Spline Garden Tractor Pulling 1 Inch",
        "Price": "$200.00",
        "Image URL": "https://i.ebayimg.com/thumbs/images/g/X3oAAOSwKJNjol3v/s-l225.jpg"
    },
    {
        "Title": "Pair LED headlight bulbs for Deere X354 X360 X370 X380 X384 X390 X394 425",
        "Price": "$17.99",
        "Image URL": "https://i.ebayimg.com/thumbs/images/g/DzUAAOSwlgRjQ8jx/s-l225.jpg"
    },
    {
        "Title": "NEW PTO Clutch Belt Fits Cub Cadet 954-3003A for 682 782 1811 Garden Tractors",
        "Price": "$24.95",
        "Image URL": "https://i.ebayimg.com/thumbs/images/g/UOUAAOSwpDdVEuK4/s-l225.jpg"
    },
    {
        "Title": "AM141075 Electronic Control Unit Module for John Deere Lawn Garden Tractor - NEW",
        "Price": "$77.27",
        "Image URL": "https://i.ebayimg.com/thumbs/images/g/mgsAAOSwB1hkN3SX/s-l225.jpg"
    },
    {
        "Title": "4 WHEEL HORSE GARDEN TRACTOR PULLING FRONT WHEEL BEARINGS GRAVELY JOHN DEERE MTD",
        "Price": "$22.00",
        "Image URL": "https://i.ebayimg.com/thumbs/images/g/NT0AAOxy4kpQ~Byc/s-l225.jpg"
    },
    {
        "Title": "Wheel Horse Garden Tractor Tail Light, 12 Volt, 105202, Replacement, White Base",
        "Price": "$13.95",
        "Image URL": "https://i.ebayimg.com/thumbs/images/g/ZbsAAOSwRZtfgzIi/s-l225.jpg"
    },
    {
        "Title": "DX SNAPPER GARDEN TRACTOR  VINYL DECALS ON WHITE",
        "Price": "$7.99",
        "Image URL": "https://i.ebayimg.com/thumbs/images/g/StkAAOSwYGFU1SIl/s-l225.jpg"
    },
    {
        "Title": "WHEEL HORSE/TORO LAWN GARDEN TRACTOR TEMP. FRONT HITCH RECEIVER DRAWBAR ATV",
        "Price": "$74.99",
        "Image URL": "https://i.ebayimg.com/thumbs/images/g/ux4AAOxyYANTYX55/s-l225.jpg"
    },
    {
        "Title": "GENUINE OEM TORO PART #108393 NYLON FAN-L-CW FOR TORO/WHEELHORSE GARDEN TRACTORS",
        "Price": "$27.44",
        "Image URL": "https://i.ebayimg.com/thumbs/images/g/69wAAOSw6EpcSiIb/s-l225.jpg"
    },
    {
        "Title": "Voltage Regulator for John Deere 322, 330, 332, 415 Lawn and Garden Tractors",
        "Price": "$19.99",
        "Image URL": "https://i.ebayimg.com/thumbs/images/g/OEEAAOSwsrhexoZr/s-l225.jpg"
    },
    {
        "Title": "OEM Husqvarna 578451301 Lawn Garden Tractor Deck Wash Kit Port & Coupler Washout",
        "Price": "$14.97",
        "Image URL": "https://i.ebayimg.com/thumbs/images/g/91AAAOSw9xJhEXgf/s-l225.jpg"
    },
    {
        "Title": "JOHN DEERE GARDEN TRACTOR 110 HOOD DECALS SET",
        "Price": "$45.00",
        "Image URL": "https://i.ebayimg.com/thumbs/images/g/5vEAAOSwvi5fwoS3/s-l225.jpg"
    },
    {
        "Title": "Electrical Ignition Time Delay Module For John Deere 345 GX345 425 445 AM128906",
        "Price": "$10.89",
        "Image URL": "https://i.ebayimg.com/thumbs/images/g/YsgAAOSwo49dkgLg/s-l225.jpg"
    },
    {
        "Title": "John Deere Hydraulic sight tube kit  316 318 322 330 332 420 430 garden tractor",
        "Price": "$25.00",
        "Image URL": "https://i.ebayimg.com/thumbs/images/g/PLwAAOSwZRpjTm6Q/s-l225.jpg"
    },
    {
        "Title": "Waterproof UV 72\" Long Riding Lawn Mower Tractor Cover Protector Garden Outdoor",
        "Price": "$76.99",
        "Image URL": "https://i.ebayimg.com/thumbs/images/g/bRQAAOSwDvBhxotR/s-l225.jpg"
    },
    {
        "Title": "OEM JOHN DEERE 210 212 214 216 ELECTRIC PTO CLUTCH AM38404",
        "Price": "$193.89",
        "Image URL": "https://i.ebayimg.com/thumbs/images/g/EccAAOSw9T9iNd66/s-l225.jpg"
    },
    {
        "Title": "3 SUPER Brite LED light bulbs for Deere 212 214 216 210 300 312 314 316 bulb 12v",
        "Price": "$14.24",
        "Image URL": "https://i.ebayimg.com/thumbs/images/g/g9gAAOSw6qZhpuSM/s-l225.jpg"
    },
    {
        "Title": "Bright LED light bulbs for Craftsman DYS 4500 DLT 3000 garden tractor headlights",
        "Price": "$11.66",
        "Image URL": "https://i.ebayimg.com/thumbs/images/g/eEwAAOSwlYph2QmK/s-l225.jpg"
    },
    {
        "Title": "IGNITION SWITCH KEY for Ariens Gravely 04986400 Craftsman 140403 411932 Tractors",
        "Price": "$7.49",
        "Image URL": "https://i.ebayimg.com/thumbs/images/g/hqoAAOSw7q5iin00/s-l225.jpg"
    },
    {
        "Title": "John Deere foot grips for 316 318 322 330 332 420 430 garden tractor",
        "Price": "$19.50",
        "Image URL": "https://i.ebayimg.com/thumbs/images/g/qEUAAOxyBvZTWHnU/s-l225.jpg"
    },
    {
        "Title": "JOHN DEERE  318, 420 LAWN GARDEN TRACTOR ONAN  B43 B48 FLYWHEEL 170-3714",
        "Price": "$54.99",
        "Image URL": "https://i.ebayimg.com/thumbs/images/g/7kkAAOSwv4djYw-c/s-l225.jpg"
    },
    {
        "Title": "Fuel Pump for John Deere L110 LT133 LT155 LX255 GT225 Lawn Mower Garden Tractor",
        "Price": "$12.74",
        "Image URL": "https://i.ebayimg.com/thumbs/images/g/qGkAAOSw5kBbPJhH/s-l225.jpg"
    },
    {
        "Title": "2 Headlight LED Bulbs for John Deere LX255 LX266 LX277 LX279 LX280 LX289 Tractor",
        "Price": "$7.99",
        "Image URL": "https://i.ebayimg.com/thumbs/images/g/CncAAOSwLhFkHQtX/s-l225.jpg"
    },
    {
        "Title": "NEW Husqvarna 578451301 Lawn Garden Tractor Deck Wash Kit Port & Coupler Washout",
        "Price": "$9.99",
        "Image URL": "https://i.ebayimg.com/thumbs/images/g/goEAAOSwVZxkHKRz/s-l225.jpg"
    },
    {
        "Title": "1000 Lumens LED 1156 Headlight Bulbs for John Deere",
        "Price": "$17.99",
        "Image URL": "https://i.ebayimg.com/thumbs/images/g/QtoAAOSwg7Vixptc/s-l225.jpg"
    },
    {
        "Title": "For Troy-Bilt Cub Cadet Deere Lawn Tractor 1156 12v32 Bright LED Headlight bulbs",
        "Price": "$21.36",
        "Image URL": "https://i.ebayimg.com/thumbs/images/g/QgYAAOSw1MNjQ82t/s-l225.jpg"
    },
    {
        "Title": "GENUINE OEM TORO PART # 95-3878 V-BELT FOR 48\" SIDE DISCHARGE GARDEN TRACTORS",
        "Price": "$79.99",
        "Image URL": "https://i.ebayimg.com/thumbs/images/g/BAgAAOSwZ2ZeansQ/s-l225.jpg"
    },
    {
        "Title": "New ListingSears Suburban st/10 Garden Tractor  wire harness voltage regulator",
        "Price": "$27.69",
        "Image URL": "https://i.ebayimg.com/thumbs/images/g/x7YAAOSwye1kTy4Z/s-l225.jpg"
    },
    {
        "Title": "Ignition Switch for Kohler CH11, CH12.5, CH14, CH18, CH20, CH22, CH25 Tractors",
        "Price": "$16.99",
        "Image URL": "https://i.ebayimg.com/thumbs/images/g/G8EAAOSwtP9e1rTF/s-l225.jpg"
    },
    {
        "Title": "HUSQVARNA Lawn Garden Tractor Owner Instruction MANUALS Part List VARIOUS MODELS",
        "Price": "$0.99 to $15.00",
        "Image URL": "https://i.ebayimg.com/thumbs/images/g/caEAAOSwoIZhJQ1K/s-l225.jpg"
    },
    {
        "Title": "Choke Cable 63\" for Lawn & Garden Tractor: Cub Cadet Wheel Horse John Deere Ford",
        "Price": "$24.99",
        "Image URL": "https://i.ebayimg.com/thumbs/images/g/qIwAAOSwv9hW2EqE/s-l225.jpg"
    },
    {
        "Title": "GENUINE OEM TORO PART # 6449 OIL SEAL FOR TORO GARDEN TRACTORS; REPLACES 6449P",
        "Price": "$14.99",
        "Image URL": "https://i.ebayimg.com/thumbs/images/g/RMgAAOSwbm9eFNZ2/s-l225.jpg"
    },
    {
        "Title": "GASKET SET & SEALS For 10 12 14HP KOHLER K241 K301 K321 4700401 Garden Tractors",
        "Price": "$44.95",
        "Image URL": "https://i.ebayimg.com/thumbs/images/g/e6wAAOxyjPNREK3T/s-l225.jpg"
    },
    {
        "Title": "(Pack of 4) Engine Control Cable for AYP & Husqvarna 162778, 176556, 532176556",
        "Price": "$15.49",
        "Image URL": "https://i.ebayimg.com/thumbs/images/g/FLIAAOSwUvpiKiWd/s-l225.jpg"
    },
    {
        "Title": "OIL FILTER fits John Deere L100 L105 L107 L108 L110 L111 L118 L120 L130 Tractors",
        "Price": "$13.99",
        "Image URL": "https://i.ebayimg.com/thumbs/images/g/5AYAAOSwuKVfHuNG/s-l225.jpg"
    },
    {
        "Title": "Muffler Fits Cub Cadet Kohler K241 K301 K321 Lawn Mower Garden Tractor",
        "Price": "$49.99",
        "Image URL": "https://i.ebayimg.com/thumbs/images/g/xyMAAOSwHRRj6yS5/s-l225.jpg"
    },
    {
        "Title": "Brake Safety  Cable for Lawn-Boy 10662, 10682 & 10780 Walk Behind Push Lawnmower",
        "Price": "$11.99",
        "Image URL": "https://i.ebayimg.com/thumbs/images/g/V5oAAOSweIxgwPlK/s-l225.jpg"
    },
    {
        "Title": "Sears Suburban Garden Tractor Fuel Tank Gas Tank Small Engine Steel Metal",
        "Price": "$49.99",
        "Image URL": "https://i.ebayimg.com/thumbs/images/g/yRAAAOSwBYBj75HN/s-l225.jpg"
    },
    {
        "Title": "JOHN DEERE Genuine OEM Transmission Pulley AM126129 LX SABRE Garden Tractors",
        "Price": "$85.74",
        "Image URL": "https://i.ebayimg.com/thumbs/images/g/liwAAMXQmWdRHMN6/s-l225.jpg"
    },
    {
        "Title": "WHEEL HORSE/TORO LAWN GARDEN TRACTOR FRONT TOW HITCH",
        "Price": "$49.99",
        "Image URL": "https://i.ebayimg.com/thumbs/images/g/yxIAAOSwfR1Zb4HR/s-l225.jpg"
    },
    {
        "Title": "2 LED light bulb for Husqvarna Deere lawn mower riding tractor AD2062R 1156",
        "Price": "$8.68",
        "Image URL": "https://i.ebayimg.com/thumbs/images/g/NTYAAOSw0w1hsxv0/s-l225.jpg"
    },
    {
        "Title": "TWO 20x10x8 Tire Fits Toro Lawn Garden Tractor Riding Mower Tubeless 4PR 20x10-8",
        "Price": "$119.88",
        "Image URL": "https://i.ebayimg.com/thumbs/images/g/XHgAAOSwc7dhLSVO/s-l225.jpg"
    },
    {
        "Title": "John Deere foot grips for  420 430 garden tractor",
        "Price": "$19.50",
        "Image URL": "https://i.ebayimg.com/thumbs/images/g/37EAAOSw319c6Tmv/s-l225.jpg"
    },
    {
        "Title": "808656 Fuel pump for Craftsman 26 Hp 54 In Deck Dgs 6500 Garden Tractor",
        "Price": "$11.43",
        "Image URL": "https://i.ebayimg.com/thumbs/images/g/udsAAOSwqXxi4huD/s-l225.jpg"
    },
    {
        "Title": "Garden Tractor Tail Light 2 Pack, Massey Ferguson MF 14,16, Ford LGT, Bolens",
        "Price": "$24.95",
        "Image URL": "https://i.ebayimg.com/thumbs/images/g/CGMAAOSwD1Fh8aF9/s-l225.jpg"
    },
    {
        "Title": "JOHN DEERE GARDEN TRACTOR 210 HOOD DECALS SET",
        "Price": "$45.00",
        "Image URL": "https://i.ebayimg.com/thumbs/images/g/hQoAAOSwOzVkNIfd/s-l225.jpg"
    },
    {
        "Title": "3 inch Drive Shaft Coupler CNC Cub Cadet Pulling Tractor Garden 100 70 1200 1250",
        "Price": "$32.50",
        "Image URL": "https://i.ebayimg.com/thumbs/images/g/vq4AAOSwHmhV8PrD/s-l225.jpg"
    },
    {
        "Title": "Cub Cadet Garden Tractor Rear Fender Reflector Replacement 2 Pack, (Tail Light)",
        "Price": "$16.95",
        "Image URL": "https://i.ebayimg.com/thumbs/images/g/5DMAAOSwB5VgXqR~/s-l225.jpg"
    },
    {
        "Title": "Mower Blade Balancer & Sharpener Set For Lawn Mower Tractor Garden Tool Part",
        "Price": "$4.14",
        "Image URL": "https://i.ebayimg.com/thumbs/images/g/y3EAAOSwt1VgkMkx/s-l225.jpg"
    },
    {
        "Title": "METAL JOHN DEERE 400 GARDEN TRACTOR FENDER DECK PLASTIC PANEL REPLACES M80695",
        "Price": "$38.14",
        "Image URL": "https://i.ebayimg.com/thumbs/images/g/RMsAAOSwUHleFz~0/s-l225.jpg"
    },
    {
        "Title": "GENUINE OEM TORO PART # 103125 SPRING FOR RIDING GARDEN TRACTORS ; REPL 103125P",
        "Price": "$22.96",
        "Image URL": "https://i.ebayimg.com/thumbs/images/g/pWYAAOSwcV5eMGzM/s-l225.jpg"
    },
    {
        "Title": "Carburetor with Gaskets for Briggs & Stratton 92502, 92508, 92902, 92982, 93902",
        "Price": "$16.99",
        "Image URL": "https://i.ebayimg.com/thumbs/images/g/FJQAAOSw7GViBWjq/s-l225.jpg"
    },
    {
        "Title": "Wheel Horse Garden /Lawn Tractor Light Switch, 20 Amp Rocker Switch, Rectangular",
        "Price": "$12.95",
        "Image URL": "https://i.ebayimg.com/thumbs/images/g/cboAAOSwHbRfPbQe/s-l225.jpg"
    },
    {
        "Title": "GENUINE OEM TORO PART # 108501 GARDEN TRACTOR TRANSMISSION DRIVE V-BELT",
        "Price": "$41.13",
        "Image URL": "https://i.ebayimg.com/thumbs/images/g/E1wAAOSwiT1cJ8Fc/s-l225.jpg"
    },
    {
        "Title": "Deck Drive Belt Fits CASTEL GARDEN TC102 TWIN CUT Lawn Tractor",
        "Price": "$17.95",
        "Image URL": "https://i.ebayimg.com/thumbs/images/g/~0kAAOSwDk5UGVqd/s-l225.jpg"
    },
    {
        "Title": "For John Deere 1025R 2025R 2032R 2038R 2017-2021 LED H4 Headlights 25000LM",
        "Price": "$17.24",
        "Image URL": "https://i.ebayimg.com/thumbs/images/g/K~0AAOSwGidjCJB2/s-l225.jpg"
    },
    {
        "Title": "PAIR LED light bulbs for Craftsman LT 2000 LT1000 LT11 garden tractor bulb",
        "Price": "$23.98",
        "Image URL": "https://i.ebayimg.com/thumbs/images/g/ZCwAAOSwLkRkEA9G/s-l225.jpg"
    },
    {
        "Title": "Shop on eBay",
        "Price": "$20.00",
        "Image URL": "https://ir.ebaystatic.com/rs/v/fxxj3ttftm5ltcqnto1o4baovyl.png"
    },
    {
        "Title": "PAIR LED light bulbs for Craftsman LT 2000 LT1000 LT11 garden tractor bulb",
        "Price": "$23.98",
        "Image URL": "https://i.ebayimg.com/thumbs/images/g/ZCwAAOSwLkRkEA9G/s-l225.jpg"
    },
    {
        "Title": "SUPER Bright LED light Bulbs For Cub Cadet LTX1040 LTX1042 LTX1045 LTX1050 mower",
        "Price": "$25.99",
        "Image URL": "https://i.ebayimg.com/thumbs/images/g/OVUAAOSwE4Fi1Q-Y/s-l225.jpg"
    },
    {
        "Title": "018543 Muffler For 12 To 16 HP Engines Gravely Garden Tractors",
        "Price": "$55.99",
        "Image URL": "https://i.ebayimg.com/thumbs/images/g/l9YAAOSwY2xiouNk/s-l225.jpg"
    },
    {
        "Title": "For John Deere 1025R 2025R 2032R 2038R 2017-2021 LED H4 Headlights 25000LM",
        "Price": "$17.24",
        "Image URL": "https://i.ebayimg.com/thumbs/images/g/K~0AAOSwGidjCJB2/s-l225.jpg"
    },
    {
        "Title": "48\" MOWER DECK BELT COMBO 174368 & 180808",
        "Price": "$21.95",
        "Image URL": "https://i.ebayimg.com/thumbs/images/g/OK0AAOSwz8tjzpzV/s-l225.jpg"
    },
    {
        "Title": "Deck Drive Belt Fits CASTEL GARDEN TC102 TWIN CUT Lawn Tractor",
        "Price": "$17.95",
        "Image URL": "https://i.ebayimg.com/thumbs/images/g/~0kAAOSwDk5UGVqd/s-l225.jpg"
    },
    {
        "Title": "JOHN DEERE C210F LAWN & GARDEN TRACTOR SHIFT GUIDE",
        "Price": "$14.99",
        "Image URL": "https://i.ebayimg.com/thumbs/images/g/b0YAAOSwoJBf3k00/s-l225.jpg"
    },
    {
        "Title": "DX SALE - GRAVELY GARDEN TRACTOR WHITE  VINYL DECALS - STICKERS",
        "Price": "$5.99",
        "Image URL": "https://i.ebayimg.com/thumbs/images/g/9OcAAMXQO21RsJEZ/s-l225.jpg"
    },
    {
        "Title": "JOHN DEERE GARDEN TRACTOR 330 HOOD DECALS SET",
        "Price": "$45.00",
        "Image URL": "https://i.ebayimg.com/thumbs/images/g/y2IAAOSwknJXz5G4/s-l225.jpg"
    },
    {
        "Title": "Replacement John Deere Lawn & Garden Tractor Drive Axle Oil Seal Replaces M48934",
        "Price": "$17.99",
        "Image URL": "https://i.ebayimg.com/thumbs/images/g/yMIAAOSw4-Rf0-Rd/s-l225.jpg"
    },
    {
        "Title": "33SMD Headlight LED Bulb for John Deere D100 D110 D120 D125 D130 D140 D150 D160",
        "Price": "$8.99",
        "Image URL": "https://i.ebayimg.com/thumbs/images/g/NdAAAOSwMX5kAEYP/s-l225.jpg"
    },
    {
        "Title": "2 Blinding Brite LED headlight bulbs for Deere 415 420 425 445 455 mower tractor",
        "Price": "$9.38",
        "Image URL": "https://i.ebayimg.com/thumbs/images/g/ePQAAOSwupVkHQtX/s-l225.jpg"
    },
    {
        "Title": "New Cub Cadet ISO Motor Mounts 1000 1200 1250 1450 1650",
        "Price": "$29.95",
        "Image URL": "https://i.ebayimg.com/thumbs/images/g/DusAAMXQWuRQ~cNh/s-l225.jpg"
    },
    {
        "Title": "Bright LED light bulbs for Craftsman DYS 4500 DLT 3000 garden tractor headlights",
        "Price": "$13.99",
        "Image URL": "https://i.ebayimg.com/thumbs/images/g/0YkAAOSwOX9kEA8m/s-l225.jpg"
    },
    {
        "Title": "Pair LED light bulbs for  Deere Kubota 1156 headlights mower rider",
        "Price": "$17.99",
        "Image URL": "https://i.ebayimg.com/thumbs/images/g/Lm0AAOSwFRxixptb/s-l225.jpg"
    },
    {
        "Title": "2 Super LED headlights For  Deere x570 X580 X584 X590; bulbs bulb light lights",
        "Price": "$12.66",
        "Image URL": "https://i.ebayimg.com/thumbs/images/g/o20AAOSwnZFkHQtZ/s-l225.jpg"
    },
    {
        "Title": "Self Propel 22\" Recycler Front Wheel Lawn Mower Traction Cable for Toro 105-1845",
        "Price": "$11.99",
        "Image URL": "https://i.ebayimg.com/thumbs/images/g/dzwAAOSwrQpkCNeM/s-l225.jpg"
    },
    {
        "Title": "John Deere Front Bumper LX Lawn Mower Garden Tractor LX266 LX277 \"MADE IN USA!!\"",
        "Price": "$129.98",
        "Image URL": "https://i.ebayimg.com/thumbs/images/g/DPMAAOSwQ2NhCCTA/s-l225.jpg"
    },
    {
        "Title": "Case Ingersoll Garden Tractor 220 222 444 446\u00a0 Fan C16616",
        "Price": "$28.50",
        "Image URL": "https://i.ebayimg.com/thumbs/images/g/I9EAAOSwTM5ew98w/s-l225.jpg"
    },
    {
        "Title": "Front Steering RH & LH Spindle Kit for John Deere L110, L111, L118, L120, L130",
        "Price": "$56.99",
        "Image URL": "https://i.ebayimg.com/thumbs/images/g/MF4AAOSwM~1gopY3/s-l225.jpg"
    },
    {
        "Title": "JOHN DEERE  425,445    LAWN&GARDEN TRACTOR  STARTER",
        "Price": "$25.00",
        "Image URL": "https://i.ebayimg.com/thumbs/images/g/cK4AAOSw4rhiArH7/s-l225.jpg"
    },
    {
        "Title": "GENUINE OEM TORO PART # 100441 OIL SEAL FOR GARDEN TRACTORS; REPL 100441P, 1303",
        "Price": "$9.85",
        "Image URL": "https://i.ebayimg.com/thumbs/images/g/wfoAAOSwT9NeNGpc/s-l225.jpg"
    },
    {
        "Title": "SUPER Bright LED light bulbs for Deere X330 X370 AD1062R X350 X354 2x",
        "Price": "$11.19",
        "Image URL": "https://i.ebayimg.com/thumbs/images/g/6E4AAOSwyU9iXjJ4/s-l225.jpg"
    },
    {
        "Title": "OEM MURRAY 37x57  LAWN GARDEN TRACTOR Deck BELT !",
        "Price": "$7.00",
        "Image URL": "https://i.ebayimg.com/thumbs/images/g/FnkAAOSwK9RkJ2b-/s-l225.jpg"
    },
    {
        "Title": "for John Deere Lawn and Garden Tractor GX325 GX335 GX345 GX355 Drive Belt",
        "Price": "$20.98",
        "Image URL": "https://i.ebayimg.com/thumbs/images/g/fWsAAOSwQkNgZW~U/s-l225.jpg"
    },
    {
        "Title": "John Deere Front Bumper GT LX Series Lawn Garden Tractor GT235 GT245 LX280 LX289",
        "Price": "$134.99",
        "Image URL": "https://i.ebayimg.com/thumbs/images/g/0AkAAOSw2qFhCCqx/s-l225.jpg"
    },
    {
        "Title": "1972 Simplicity Sovereign 3415H Garden Tractor Part : Headlights",
        "Price": "$19.99",
        "Image URL": "https://i.ebayimg.com/thumbs/images/g/lzYAAOSwZqdkRY0O/s-l225.jpg"
    },
    {
        "Title": "Electric PTO Clutch for Cub Cadet 917170056, 917532140923, 917532170056 Motor",
        "Price": "$139.99",
        "Image URL": "https://i.ebayimg.com/thumbs/images/g/WKkAAOSwiyFi4WAQ/s-l225.jpg"
    },
    {
        "Title": "Waterproof UV 72\" Long Riding Lawn Mower Tractor Cover Protector Garden Outdoor",
        "Price": "$76.99",
        "Image URL": "https://i.ebayimg.com/thumbs/images/g/bRQAAOSwDvBhxotR/s-l225.jpg"
    },
    {
        "Title": "Super Bright LED Light Bulbs for Deere x570 X580 X584 X590  655 755 855 955",
        "Price": "$25.87",
        "Image URL": "https://i.ebayimg.com/thumbs/images/g/CkQAAOSwQL5iqZV~/s-l225.jpg"
    },
    {
        "Title": "Bright LED light bulb for Husqvarna Deere lawn mower riding tractor AD2062R 1156",
        "Price": "$15.36",
        "Image URL": "https://i.ebayimg.com/thumbs/images/g/sZAAAOSwYh5h1VRS/s-l225.jpg"
    },
    {
        "Title": "4 SUPER BRIGHT LED light bulbs for Craftsman LT 2000 LT1000 LT11 garden tractor",
        "Price": "$25.99",
        "Image URL": "https://i.ebayimg.com/thumbs/images/g/g98AAOSwSPpjFrCb/s-l225.jpg"
    },
    {
        "Title": "New Plastic Headlight Lens for Vintage Garden Tractors Ford LGT, Case, Ingersoll",
        "Price": "$14.99",
        "Image URL": "https://i.ebayimg.com/thumbs/images/g/lJAAAOSw3l9gkqvK/s-l225.jpg"
    },
    {
        "Title": "SNAPPER COMET  GARDEN TRACTOR VINYL DECALS",
        "Price": "$25.00",
        "Image URL": "https://i.ebayimg.com/thumbs/images/g/i3kAAOSwr91i0Z9h/s-l225.jpg"
    },
    {
        "Title": "Universal replacement starter solenoid fit for most lawn garden tractors-",
        "Price": "$9.89 to $12.62",
        "Image URL": "https://i.ebayimg.com/thumbs/images/g/D0AAAOSwI3Fj~EH0/s-l225.jpg"
    },
    {
        "Title": "JOHN DEERE  425,445   LAWN & GARDEN TRACTOR  DRIVE SHAFT",
        "Price": "$20.00",
        "Image URL": "https://i.ebayimg.com/thumbs/images/g/42QAAOSwcDJj2T4l/s-l225.jpg"
    },
    {
        "Title": "Seat Fits John Deere GX255 GX325 GX335 GX345 GX355 LX266 LX277 LX279 AM131531",
        "Price": "$210.99",
        "Image URL": "https://i.ebayimg.com/thumbs/images/g/Q5wAAOSwaEtiotmJ/s-l225.jpg"
    },
    {
        "Title": "New carburetor Assembly For John Deere GX255 - TRACTOR, LAWN AND GARDEN",
        "Price": "$65.45",
        "Image URL": "https://i.ebayimg.com/thumbs/images/g/mCUAAOSw2jdfIaIw/s-l225.jpg"
    },
    {
        "Title": "SUPER Bright LED light bulbs For  LTX1040 LTX1042 LTX1045 LTX1050 mower",
        "Price": "$13.99",
        "Image URL": "https://i.ebayimg.com/thumbs/images/g/94oAAOSwyI9kEA8m/s-l225.jpg"
    },
    {
        "Title": "3 SUPER LED light bulbs for Deere 655 755 855 955 headlights tractor bulb mower",
        "Price": "$22.99",
        "Image URL": "https://i.ebayimg.com/thumbs/images/g/xo8AAOSwvuthpuSI/s-l225.jpg"
    },
    {
        "Title": "John Deere LG181 Home Maintenance Service Kit 318 Series Lawn & Garden Tractors",
        "Price": "$49.99",
        "Image URL": "https://i.ebayimg.com/thumbs/images/g/9rsAAOSwYINj92pt/s-l225.jpg"
    },
    {
        "Title": "Carburetor with Linkage Kit for Kohler K241 K301 Cast Iron 10 & 12 HP K-Series",
        "Price": "$39.99",
        "Image URL": "https://i.ebayimg.com/thumbs/images/g/yKMAAOSwiphiaqpu/s-l225.jpg"
    },
    {
        "Title": "JOHN DEER  318   LAWN & GARDEN TRACTOR ONAN B43G,B48G STATOR",
        "Price": "$15.00",
        "Image URL": "https://i.ebayimg.com/thumbs/images/g/1KQAAOSwSPlgc4qD/s-l225.jpg"
    },
    {
        "Title": "Case Ingersoll Lawn Mower Garden Tractor Hydro Transmission Oil Filter C37637",
        "Price": "$32.87",
        "Image URL": "https://i.ebayimg.com/thumbs/images/g/iI8AAOSwWhRZgca3/s-l225.jpg"
    },
    {
        "Title": "GENUINE OEM TORO PART # 100-3524 SWITCH-SEAT FOR GARDEN TRACTORS & ZERO TURNS",
        "Price": "$46.01",
        "Image URL": "https://i.ebayimg.com/thumbs/images/g/-v0AAOSwQZdcJmn9/s-l225.jpg"
    },
    {
        "Title": "Oregon Lawn Mower Garden Tractor Deck Leveling Gauge 42-095",
        "Price": "$13.71",
        "Image URL": "https://i.ebayimg.com/thumbs/images/g/Q0EAAOSwUchaBJ~A/s-l225.jpg"
    },
    {
        "Title": "D=  PAIR OF WHEEL HORSE GARDEN TRACTOR DECALS 1LT&1RT 549",
        "Price": "$11.99",
        "Image URL": "https://i.ebayimg.com/thumbs/images/g/HVIAAOSwEphgLngX/s-l225.jpg"
    },
    {
        "Title": "Fuel Pump for John Deere 240 245 260 265 285 320 GX345 Lawn & Garden Tractor",
        "Price": "$15.98",
        "Image URL": "https://i.ebayimg.com/thumbs/images/g/zWwAAOSw0F9bog9y/s-l225.jpg"
    },
    {
        "Title": "LED Headlight Bulb for Riding Lawn Tractor Riding Lawn Mower Snow 1156 Deere Cub",
        "Price": "$7.99",
        "Image URL": "https://i.ebayimg.com/thumbs/images/g/l~MAAOSw2r1kHQtX/s-l225.jpg"
    },
    {
        "Title": "6 Sears Craftsman Upper & Lower Spindle Bearing Sealed Bearings",
        "Price": "$19.90",
        "Image URL": "https://i.ebayimg.com/thumbs/images/g/~bEAAOSwUPZbMSuq/s-l225.jpg"
    },
    {
        "Title": "OIL FILTER fits John Deere L100 L105 L107 L108 L110 L111 L118 L120 L130 Tractors",
        "Price": "$13.99",
        "Image URL": "https://i.ebayimg.com/thumbs/images/g/5AYAAOSwuKVfHuNG/s-l225.jpg"
    },
    {
        "Title": "Ignition Key Replacement Fits Husqvarna Riding Garden Lawn Mower Tractor",
        "Price": "$7.99",
        "Image URL": "https://i.ebayimg.com/thumbs/images/g/384AAOSwbGViin5O/s-l225.jpg"
    },
    {
        "Title": "JOHN DEERE 425,445,345  LAWN&GARDEN TRACTOR KAWASKI VALVE COVER",
        "Price": "$8.00",
        "Image URL": "https://i.ebayimg.com/thumbs/images/g/sscAAOSw4eVgxoLd/s-l225.jpg"
    },
    {
        "Title": "Ignition Key Switch Garden Tractor Magneto Ignition Wheel Horse John Deere Cub",
        "Price": "$14.99",
        "Image URL": "https://i.ebayimg.com/thumbs/images/g/O54AAOSwjVVVzzSQ/s-l225.jpg"
    },
    {
        "Title": "Stop Cable for Craftsman 917377190, 917377200, 917377201 & 917377210 Push Mower",
        "Price": "$9.99",
        "Image URL": "https://i.ebayimg.com/thumbs/images/g/kx0AAOSw4UJgv9nk/s-l225.jpg"
    },
    {
        "Title": "CASE/Ingersoll Garden Tractor Front Wheel Dust Cap C-26021",
        "Price": "$6.25",
        "Image URL": "https://i.ebayimg.com/thumbs/images/g/G1AAAOxylhxRGGRk/s-l225.jpg"
    },
    {
        "Title": "Garden Tractor Throttle Control Cable Assembly Cub Cadet Ford John Deere Gravely",
        "Price": "$39.99",
        "Image URL": "https://i.ebayimg.com/thumbs/images/g/xD0AAOSwv~xXDY35/s-l225.jpg"
    },
    {
        "Title": "Ignition Coil For Craftsman GT3000 GT-5000 Garden Tractor Kohler Pro 23HP 25HP",
        "Price": "$14.25",
        "Image URL": "https://i.ebayimg.com/thumbs/images/g/k~wAAOSwQz5jTOse/s-l225.jpg"
    },
    {
        "Title": "Carburetor Carb Craftsman  LT11/36 11hp Garden Riding Tractor Lawn Mower Briggs",
        "Price": "$59.95",
        "Image URL": "https://i.ebayimg.com/thumbs/images/g/3YQAAOSw~Axgc4uG/s-l225.jpg"
    },
    {
        "Title": "JOHN DEER 425,445,455,345  LAWN & GARDEN TRACTOR STEERING BOX",
        "Price": "$40.00",
        "Image URL": "https://i.ebayimg.com/thumbs/images/g/ZtwAAOSw~7dfLypT/s-l225.jpg"
    },
    {
        "Title": "2 Blinding Brite LED headlight bulbs for Deere 415 425 445 455 355 mower tractor",
        "Price": "$17.99",
        "Image URL": "https://i.ebayimg.com/thumbs/images/g/9LAAAOSwvzZh831I/s-l225.jpg"
    },
    {
        "Title": "Belt Pulley Fits CASTEL GARDEN TC92 TC102 TC122 Ride On Tractor",
        "Price": "$6.77",
        "Image URL": "https://i.ebayimg.com/thumbs/images/g/wUoAAOSw-jhUK93e/s-l225.jpg"
    },
    {
        "Title": "Tune Up Maintenance Service Filter Kit For John Deere X520 X540 Garden Tractors",
        "Price": "$59.99",
        "Image URL": "https://i.ebayimg.com/thumbs/images/g/KwwAAOSwcwhVQPcf/s-l225.jpg"
    },
    {
        "Title": "DX 2-  ( INTERNATIONAL CUB CADET ) GARDEN TRACTOR DECALS 2.5\" x 8.5\"",
        "Price": "$9.99",
        "Image URL": "https://i.ebayimg.com/thumbs/images/g/OCIAAMXQkl9Rawmo/s-l225.jpg"
    },
    {
        "Title": "JOHN DEERE  GT225  GT235  GT245  Garden Tractor Steering Upgrade",
        "Price": "$17.49",
        "Image URL": "https://i.ebayimg.com/thumbs/images/g/rncAAOSw9lVfEOQx/s-l225.jpg"
    },
    {
        "Title": "Cub Cadet Motor Engine ISO Mounts Quiet Line Tractors",
        "Price": "$29.95",
        "Image URL": "https://i.ebayimg.com/thumbs/images/g/BXUAAOxy4kpQ~Yk0/s-l225.jpg"
    },
    {
        "Title": "Wheel Horse Garden Tractor Tail Lights, 12 Volt, 105202, Replacement, Set of 2",
        "Price": "$24.95",
        "Image URL": "https://i.ebayimg.com/thumbs/images/g/~AMAAOSwdQtgoYD6/s-l225.jpg"
    },
    {
        "Title": "Pinion Gear for John Deere L118 - PC9358, L120 - PC9290, L130 - PC9291 Tractors",
        "Price": "$8.99",
        "Image URL": "https://i.ebayimg.com/thumbs/images/g/47EAAOSwx2liTFPB/s-l225.jpg"
    },
    {
        "Title": "Ignition Switch with Keys for 1989, 414-8 Toro 31-14K804 Yard Garden Tractors",
        "Price": "$16.99",
        "Image URL": "https://i.ebayimg.com/thumbs/images/g/G8EAAOSwtP9e1rTF/s-l225.jpg"
    },
    {
        "Title": "JOHN DEERE Genuine OEM Transmission Filter Kit 325 335 345 355D AM120916 M806848",
        "Price": "$105.77",
        "Image URL": "https://i.ebayimg.com/thumbs/images/g/SPEAAOxyQBJREL8p/s-l225.jpg"
    },
    {
        "Title": "Carburetor for Tecumseh 631921, 631070, 631070A, 631074, 631245, 631820, 632284",
        "Price": "$21.99",
        "Image URL": "https://i.ebayimg.com/thumbs/images/g/IiYAAOSwIrpiBXc2/s-l225.jpg"
    },
    {
        "Title": "NEW GENUINE OEM TORO PART # 114895 V-BELT FOR GARDEN TRACTORS; REPLACES 112801",
        "Price": "$31.94",
        "Image URL": "https://i.ebayimg.com/thumbs/images/g/7DwAAOSwtjBeF13A/s-l225.jpg"
    },
    {
        "Title": "CUB CADET 753-08658 Engine Oil Drain Kit Enduro XT1-LT42C Lawn Garden Tractors",
        "Price": "$11.99",
        "Image URL": "https://i.ebayimg.com/thumbs/images/g/2LoAAOSwmuVjHd-z/s-l225.jpg"
    },
    {
        "Title": "Bright LED light bulb for Husqvarna Deere lawn mower riding tractor AD2062R 1156",
        "Price": "$14.11",
        "Image URL": "https://i.ebayimg.com/thumbs/images/g/JfgAAOSwQ51h5SsR/s-l225.jpg"
    },
    {
        "Title": "Pair LED light bulbs for Craftsman T135 T105 E225 headlights light mower",
        "Price": "$12.98",
        "Image URL": "https://i.ebayimg.com/thumbs/images/g/48EAAOSwuyZkNhXa/s-l225.jpg"
    },
    {
        "Title": "Shop on eBay",
        "Price": "$20.00",
        "Image URL": "https://ir.ebaystatic.com/rs/v/fxxj3ttftm5ltcqnto1o4baovyl.png"
    },
    {
        "Title": "Ariens Gravely Flat Idler Pulley 07309300 For 40\" Deck Lawn & Garden Tractors",
        "Price": "$42.87",
        "Image URL": "https://i.ebayimg.com/thumbs/images/g/n6gAAOSw7NNUJHIx/s-l225.jpg"
    },
    {
        "Title": "LED Headlight Bulbs for Riding Lawn Tractor,Riding Lawn Mower,Snow, 1156, White",
        "Price": "$15.99",
        "Image URL": "https://i.ebayimg.com/thumbs/images/g/d5IAAOSwVu9kHQta/s-l225.jpg"
    },
    {
        "Title": "SUPER Bright LED light bulbs for Cub Cadet LTX1040 LTX1042 LTX1045 LTX1050 mower",
        "Price": "$24.99",
        "Image URL": "https://i.ebayimg.com/thumbs/images/g/7L8AAOSwjyNjFrwQ/s-l225.jpg"
    },
    {
        "Title": "Brite LED light bulbs for  LT1024 LT1040 LT1042 LT1045 bulb headlights",
        "Price": "$15.99",
        "Image URL": "https://i.ebayimg.com/thumbs/images/g/nMYAAOSwKq9g~hmi/s-l225.jpg"
    },
    {
        "Title": "Craftsman Sears AYP 140462 garden tractor HYDRO TRANSAXLE FAN 7\" OEM 532140462",
        "Price": "$15.00",
        "Image URL": "https://i.ebayimg.com/thumbs/images/g/ewoAAOSwf3peurbG/s-l225.jpg"
    },
    {
        "Title": "IGNITION COIL Module Magneto for Tecumseh 36344A, 37137, 36344 Lawn Mower Motors",
        "Price": "$24.99",
        "Image URL": "https://i.ebayimg.com/thumbs/images/g/rWAAAOSwJ4hY-QJB/s-l225.jpg"
    },
    {
        "Title": "CASE/Ingersoll 3010 3012 3016 3018 3014 Tractor Speaker 780 Headlight lens",
        "Price": "$19.99",
        "Image URL": "https://i.ebayimg.com/thumbs/images/g/eQEAAOSwYFlj0Ern/s-l225.jpg"
    },
    {
        "Title": "John Deere Front Bumper LX Lawn Mower Garden Tractor LX279 LX288 \"MADE IN USA!!\"",
        "Price": "$129.98",
        "Image URL": "https://i.ebayimg.com/thumbs/images/g/M0EAAOSwFKxhCCYN/s-l225.jpg"
    },
    {
        "Title": "Starter Solenoid for Ariens 936072 (960460053-00) & Gravely 44123 1232-G Mower",
        "Price": "$15.49",
        "Image URL": "https://i.ebayimg.com/thumbs/images/g/ZgYAAOSweK9hwI1y/s-l225.jpg"
    },
    {
        "Title": "John Deere Onan 316 318 - B43 Driveshaft",
        "Price": "$39.99",
        "Image URL": "https://i.ebayimg.com/thumbs/images/g/NPcAAOSw39Be7kEe/s-l225.jpg"
    },
    {
        "Title": "10x 1/4 \" inline fuel shut off valve for briggs & stratton 494768 698183 120-212",
        "Price": "$11.52",
        "Image URL": "https://i.ebayimg.com/thumbs/images/g/N84AAOSwQMdjmE1Q/s-l225.jpg"
    },
    {
        "Title": "JOHN DEERE Genuine OEM IGNITION Coil KOHLER ENGINES M133019 LX L LT SABRE STX",
        "Price": "$32.96",
        "Image URL": "https://i.ebayimg.com/thumbs/images/g/D-YAAOxylhxRFfwq/s-l225.jpg"
    },
    {
        "Title": "Ignition Coil For Craftsman GT3000 GT-5000 Garden Tractor Kohler Pro 23HP 25HP",
        "Price": "$14.25",
        "Image URL": "https://i.ebayimg.com/thumbs/images/g/p70AAOSwR9ZjTjZ0/s-l225.jpg"
    },
    {
        "Title": "White LED light bulbs for Deere Sabre headlight mower tractor rider bulb lights",
        "Price": "$23.98",
        "Image URL": "https://i.ebayimg.com/thumbs/images/g/X~8AAOSwgW5kEA8m/s-l225.jpg"
    },
    {
        "Title": "Pair LED light bulbs for Craftsman T135 T105 E225 headlights light mower",
        "Price": "$15.98",
        "Image URL": "https://i.ebayimg.com/thumbs/images/g/kW8AAOSwwu1kEA-1/s-l225.jpg"
    },
    {
        "Title": "CHUSYYRAY SUPER Bright LED For lawn tractor Headlight tail bulb1156 bulbs mower",
        "Price": "$22.99",
        "Image URL": "https://i.ebayimg.com/thumbs/images/g/QYcAAOSwWcRkPOXB/s-l225.jpg"
    },
    {
        "Title": "MIU11376 Paper Air Filter Fits John Deere Lawn & Garden Tractors: 425, 445, 455",
        "Price": "$22.44",
        "Image URL": "https://i.ebayimg.com/thumbs/images/g/~VEAAOSwRgljoAC~/s-l225.jpg"
    },
    {
        "Title": "Carburetor Rebuild Kit for Cub Cadet Garden Tractor 1450, 1650, 1710, 1711, 1712",
        "Price": "$8.99",
        "Image URL": "https://i.ebayimg.com/thumbs/images/g/bPkAAOSwzh1i7RCa/s-l225.jpg"
    },
    {
        "Title": "Blade Control Cable for 2009 Troy-Bilt 12A-466M011 & 12A-466M066 Lawn Mower",
        "Price": "$9.49",
        "Image URL": "https://i.ebayimg.com/thumbs/images/g/Ii0AAOSw45xguh5z/s-l225.jpg"
    },
    {
        "Title": "Two Brake Pad Puck MIA10323 Fits John Deere Fits JD 170 175 180 185 STX30 STX38",
        "Price": "$22.99",
        "Image URL": "https://i.ebayimg.com/thumbs/images/g/h0cAAOSwT~Zioujl/s-l225.jpg"
    },
    {
        "Title": "Cub Cadet Garden Tractor Ross Easy Steering Upgrade Kit For 129,149,169 & 800",
        "Price": "$16.75",
        "Image URL": "https://i.ebayimg.com/thumbs/images/g/b0oAAOSwRo9j1yNo/s-l225.jpg"
    },
    {
        "Title": "Pair of 2 Link Tire Chains 20x10x8 for John Deere Lawn Mower & Garden Tractor",
        "Price": "$49.99",
        "Image URL": "https://i.ebayimg.com/thumbs/images/g/Z4sAAOSw9TRh5YYz/s-l225.jpg"
    },
    {
        "Title": "(Pack of 2) Genuine OEM Grasshopper Handle Grip 422179 for Tractors Mowers Lawn",
        "Price": "$14.49",
        "Image URL": "https://i.ebayimg.com/thumbs/images/g/kjMAAOSwNcxhw3gN/s-l225.jpg"
    },
    {
        "Title": "New Listing1x Carburetor Carb for John Deere 345 GX345 Garden Tractors 15003-2801",
        "Price": "$69.18",
        "Image URL": "https://i.ebayimg.com/thumbs/images/g/iIsAAOSw2EZgqQDE/s-l225.jpg"
    },
    {
        "Title": "Engine Control Cable for Poulan 96134000106, 96134000301, 96134000600 Push Mower",
        "Price": "$8.99",
        "Image URL": "https://i.ebayimg.com/thumbs/images/g/X-0AAOSwbTRiKQDi/s-l225.jpg"
    },
    {
        "Title": "PTO Clutch Switch for Bobcat 2721505, 2188153, 4172503 Tractor Mower Knob Engage",
        "Price": "$17.99",
        "Image URL": "https://i.ebayimg.com/thumbs/images/g/HdUAAOSwFTpi1War/s-l225.jpg"
    },
    {
        "Title": "NEW John Deere Front HITCH Bumper GT Series Garden Tractor GT235 GT245 USA MADE",
        "Price": "$129.97",
        "Image URL": "https://i.ebayimg.com/thumbs/images/g/pUkAAOSwO4VhqoYL/s-l225.jpg"
    },
    {
        "Title": "IGNITION KEY SWITCH & KEYS for Exmark 1-543070 Hustler 045898 Troy-Bilt 1754250P",
        "Price": "$14.99",
        "Image URL": "https://i.ebayimg.com/thumbs/images/g/ZSoAAOSw3YJZU6X4/s-l225.jpg"
    },
    {
        "Title": "LED Headlight Bulb for Riding Lawn Tractor Riding Lawn Mower Snow 1156 Deere Cub",
        "Price": "$16.61",
        "Image URL": "https://i.ebayimg.com/thumbs/images/g/nMYAAOSwKq9g~hmi/s-l225.jpg"
    },
    {
        "Title": "Pair LED light bulbs for Craftsman T135 T105 E225 headlights light mower",
        "Price": "$12.98",
        "Image URL": "https://i.ebayimg.com/thumbs/images/g/48EAAOSwuyZkNhXa/s-l225.jpg"
    },
    {
        "Title": "1- Fuel Filter Inline 1/4\" Fittings, Fits Briggs MTD Tecumseh Kohler Fits Honda",
        "Price": "$6.19",
        "Image URL": "https://i.ebayimg.com/thumbs/images/g/YJkAAOSwRodioryt/s-l225.jpg"
    },
    {
        "Title": "SUPER BRIGHT LED light bulbs for Husqvarna YTH24V48 LGT48DXL TS354D",
        "Price": "$15.98",
        "Image URL": "https://i.ebayimg.com/thumbs/images/g/e2sAAOSwNtpkEA~U/s-l225.jpg"
    },
    {
        "Title": "Pair of 2 Link Tire Chains 23x10.5x12 for John Deere Lawn Mower, Garden Tractor",
        "Price": "$54.99",
        "Image URL": "https://i.ebayimg.com/thumbs/images/g/rBEAAOSwRFZh7wEb/s-l225.jpg"
    },
    {
        "Title": "Cub Cadet Garden Tractor Steering Ball Joints - 2185 - 2166 - 2135 - 2000 series",
        "Price": "$19.99",
        "Image URL": "https://i.ebayimg.com/thumbs/images/g/QIIAAOSwUuFWtzMM/s-l225.jpg"
    },
    {
        "Title": "LED 1156  lawn tractor light bulb For John Deere LA100 LA105 LA110; 12v",
        "Price": "$7.99",
        "Image URL": "https://i.ebayimg.com/thumbs/images/g/KJoAAOSwrhhkHQtX/s-l225.jpg"
    },
    {
        "Title": "Lawn & Garden Tractor Key Switch Connector Kit Fits Wheel Horse Toro Gravely MTD",
        "Price": "$8.49",
        "Image URL": "https://i.ebayimg.com/thumbs/images/g/qFsAAOSwS51eYWMl/s-l225.jpg"
    },
    {
        "Title": "JOHN DEERE 425,445,455,LX188  LAWN & GARDEN TRACTOR HYDO PEDDEL",
        "Price": "$5.00",
        "Image URL": "https://i.ebayimg.com/thumbs/images/g/Y0kAAOSw44BYUHR9/s-l225.jpg"
    },
    {
        "Title": "(12) OIL FILTERS for Stens 120-485 Rotary 6929 Ferris 2102278X1 Hustler 602581",
        "Price": "$69.99",
        "Image URL": "https://i.ebayimg.com/thumbs/images/g/siYAAOSw2exfHuz6/s-l225.jpg"
    },
    {
        "Title": "SUPER Bright LED light bulbs for Cub Cadet LTX1040 LTX1042 LTX1045 LTX1050 mower",
        "Price": "$16.99",
        "Image URL": "https://i.ebayimg.com/thumbs/images/g/ztwAAOSwf-xhIFr0/s-l225.jpg"
    },
    {
        "Title": "LED light bulbs For AD2062R Deere 355D GT245; tractor mower headlight",
        "Price": "$17.58",
        "Image URL": "https://i.ebayimg.com/thumbs/images/g/ROkAAOSwqIRhj4bg/s-l225.jpg"
    },
    {
        "Title": "Single Terminal Electronic Ignition Module for John Deere Tractor  LX172, LX173",
        "Price": "$18.99",
        "Image URL": "https://i.ebayimg.com/thumbs/images/g/OiQAAOSweWZkEMaR/s-l225.jpg"
    },
    {
        "Title": "John Deere Sabre 1338 1538 1546 1638 LT-133 Tractor Spicer 4360 105 Transaxle",
        "Price": "$297.24",
        "Image URL": "https://i.ebayimg.com/thumbs/images/g/w80AAOSwVnlj4tc6/s-l225.jpg"
    },
    {
        "Title": "13X6.50-6 13X6.5-6 TIRE FOR LAWN MOWER GARDEN TURF TRACTOR TRAILER TUBELESS",
        "Price": "$33.71",
        "Image URL": "https://i.ebayimg.com/thumbs/images/g/J7sAAOSws9tj3CHA/s-l225.jpg"
    },
    {
        "Title": "Two 13x5.00-6 Smooth 4 Ply Tires for Lawn Garden Tractor Zero Turns 13 500 6",
        "Price": "$59.88",
        "Image URL": "https://i.ebayimg.com/thumbs/images/g/kXIAAOSwNbZhOPuF/s-l225.jpg"
    },
    {
        "Title": "Plunger Interlock Switch for John Deere TCA15398 Riding Lawn Garden Tractors",
        "Price": "$13.49",
        "Image URL": "https://i.ebayimg.com/thumbs/images/g/9NcAAOSwG7JfKYF8/s-l225.jpg"
    },
    {
        "Title": "GAS FUEL SHUT-OFF VALVE Two-Way for Zero Turn Lawn Mower ZTR Garden Tractor",
        "Price": "$30.20",
        "Image URL": "https://i.ebayimg.com/thumbs/images/g/jrkAAOSwew9ja0T7/s-l225.jpg"
    },
    {
        "Title": "DX SALE- SIMPLICITY GARDEN TRACTOR VINYL DECALS WHITE US",
        "Price": "$5.99",
        "Image URL": "https://i.ebayimg.com/thumbs/images/g/e38AAMXQpwFRaflm/s-l225.jpg"
    },
    {
        "Title": "New Case Ingersoll Lawn Mower Garden Tractor Ignition Key Starter Switch C30268",
        "Price": "$27.13",
        "Image URL": "https://i.ebayimg.com/thumbs/images/g/fsIAAOSwQJli6~FO/s-l225.jpg"
    },
    {
        "Title": "Brake Cable for 2009 Toro 20113 (SN 280000001-280999999) 22\" Recycler Lawnmower",
        "Price": "$10.49",
        "Image URL": "https://i.ebayimg.com/thumbs/images/g/xbUAAOSw4uhkB3IJ/s-l225.jpg"
    },
    {
        "Title": "John Deere Front Bumper GT GX Series Lawn Garden Tractor GT225 GT235 GT245 GX255",
        "Price": "$134.99",
        "Image URL": "https://i.ebayimg.com/thumbs/images/g/PWQAAOSwB41hCCsq/s-l225.jpg"
    },
    {
        "Title": "Ignition Key Replacement Fits Husqvarna Riding Garden Lawn Mower Tractor",
        "Price": "$8.99",
        "Image URL": "https://i.ebayimg.com/thumbs/images/g/JBQAAOSwB0tiothQ/s-l225.jpg"
    },
    {
        "Title": "Fuel Pump for John Deere L110 LT133 LT155 LX255 GT225 Lawn Mower Garden Tractor",
        "Price": "$14.02",
        "Image URL": "https://i.ebayimg.com/thumbs/images/g/2wAAAOSwDFBjfBeH/s-l225.jpg"
    },
    {
        "Title": "D= ON SALE WAS $7.99 NOW $6.99 SNAPPER GARDEN TRACTOR  VINYL DECALS ON WHITE",
        "Price": "$6.99",
        "Image URL": "https://i.ebayimg.com/thumbs/images/g/i8oAAOSwE~xa9agL/s-l225.jpg"
    },
    {
        "Title": "STARTER DRIVE for Kohler 25-098-11, 25-098-11-S, 25-098-20, 25-098-20-S",
        "Price": "$19.20",
        "Image URL": "https://i.ebayimg.com/thumbs/images/g/OUAAAOSwVcFXOqSl/s-l225.jpg"
    },
    {
        "Title": "Deck Engagement Clutch Cable for Craftsman 917270750 Riding Lawn Mower Tractor",
        "Price": "$11.99",
        "Image URL": "https://i.ebayimg.com/thumbs/images/g/nMgAAOSw-HRiGOJQ/s-l225.jpg"
    },
    {
        "Title": "Snapper 7013536 Short Belt for 42\" Snowthrower - 1600/1650 Garden Tractors - NOS",
        "Price": "$21.99",
        "Image URL": "https://i.ebayimg.com/thumbs/images/g/Rc8AAOSwYZJeF47G/s-l225.jpg"
    },
    {
        "Title": "Ignition Starter Switch for Ariens GT, 12 HP 931016 Kohler, Hydro Tractor Keys",
        "Price": "$14.99",
        "Image URL": "https://i.ebayimg.com/thumbs/images/g/LpEAAOSw~WJivu2M/s-l225.jpg"
    },
    {
        "Title": "OEM Toro Wheel Horse Lawn Mower Garden Tractor Spacer Bushing 111044 11104",
        "Price": "$6.87",
        "Image URL": "https://i.ebayimg.com/thumbs/images/g/OmsAAOSw3ZtaODM8/s-l225.jpg"
    },
    {
        "Title": "JOHN DEERE  425,445  LAWN & GARDEN TRACTOR   KAWASKI  VALVE COVER",
        "Price": "$12.00",
        "Image URL": "https://i.ebayimg.com/thumbs/images/g/hlEAAOSw-OJjAXUq/s-l225.jpg"
    },
    {
        "Title": "Ignition Switch with Keys for John Deere Tractor Mowers X500, X520, X530, X534",
        "Price": "$16.99",
        "Image URL": "https://i.ebayimg.com/thumbs/images/g/wh4AAOSwddlkNEY7/s-l225.jpg"
    },
    {
        "Title": "New Universal Snap-In DIGITAL HOUR METER - Riding Lawn Mower Garden Tractor",
        "Price": "$21.49",
        "Image URL": "https://i.ebayimg.com/thumbs/images/g/KZcAAOSwNSxVWjpy/s-l225.jpg"
    },
    {
        "Title": "John Deere 300 316 330 332 318 Tractor 50\" Mowing Deck Mule Drive Pulley",
        "Price": "$26.07",
        "Image URL": "https://i.ebayimg.com/thumbs/images/g/HmoAAOSw6DZkKgF2/s-l225.jpg"
    },
    {
        "Title": "Extension Brake Arm Spring for Craftsman Jonsered 532179748, 532131335 Mowers",
        "Price": "$7.99",
        "Image URL": "https://i.ebayimg.com/thumbs/images/g/SZgAAOSw47VgnTmd/s-l225.jpg"
    },
    {
        "Title": "\"Diesel\" Decal for John Deere X Series Garden Tractors",
        "Price": "$12.00",
        "Image URL": "https://i.ebayimg.com/thumbs/images/g/Ev8AAOSwvY5iLFNy/s-l225.jpg"
    },
    {
        "Title": "GENUINE OEM TORO PART # 112-0374 LIFT CABLE FOR LX & GT LAWN & GARDEN TRACTORS",
        "Price": "$26.96",
        "Image URL": "https://i.ebayimg.com/thumbs/images/g/aw8AAOSww-deGOgt/s-l225.jpg"
    },
    {
        "Title": "2pcs LED 1156  lawn tractor light bulb for John Deere LA100 LA105 LA110",
        "Price": "$8.88",
        "Image URL": "https://i.ebayimg.com/thumbs/images/g/r2cAAOSwb21hlbCZ/s-l225.jpg"
    },
    {
        "Title": "HUSQVARNA Lawn Garden Tractor Instruction Owner MANUALS Part List VARIOUS MODELS",
        "Price": "$0.99 to $15.00",
        "Image URL": "https://i.ebayimg.com/thumbs/images/g/IRMAAOSwCxNhJDzT/s-l225.jpg"
    },
    {
        "Title": "For Husqvarna Deere lawn mower riding tractor AD2062R 1156 2 LED light bulb",
        "Price": "$7.99",
        "Image URL": "https://i.ebayimg.com/thumbs/images/g/lIoAAOSwKmxkHQtY/s-l225.jpg"
    },
    {
        "Title": "Ignition Switch for Toro 92-6785, 926785, 101917 4 Positions and 5 Terminals Gas",
        "Price": "$16.99",
        "Image URL": "https://i.ebayimg.com/thumbs/images/g/87YAAOSw2FFkKy51/s-l225.jpg"
    },
    {
        "Title": "Universal Choke Push-Pull Control Cable for Rotary 237 Garden Mower Tractor",
        "Price": "$14.99",
        "Image URL": "https://i.ebayimg.com/thumbs/images/g/rYcAAOSw5IFiQirj/s-l225.jpg"
    },
    {
        "Title": "(Pack of 4) Engine Control Cable for 2001 - 2012 Husqvarna 5521 CM Lawn Mower",
        "Price": "$15.49",
        "Image URL": "https://i.ebayimg.com/thumbs/images/g/eKIAAOSwQ5hiKi1X/s-l225.jpg"
    },
    {
        "Title": "2x SUPER LED light bulbs for Cub Cadet LTX1040 LTX1042 LTX1045 LTX1050 mower 12v",
        "Price": "$10.23",
        "Image URL": "https://i.ebayimg.com/thumbs/images/g/KJMAAOSwLkFhtAe1/s-l225.jpg"
    },
    {
        "Title": "Electric PTO Clutch for Bobcat ZT200, ZT200D, ZT218, ZT219, ZT220ES, ZT223 Mower",
        "Price": "$159.99",
        "Image URL": "https://i.ebayimg.com/thumbs/images/g/h2UAAOSwptdjD4Dq/s-l225.jpg"
    },
    {
        "Title": "BRIGHT LED light bulbs For  LT1046 LT1050 GT3100 GT3200 lights tractor",
        "Price": "$16.98",
        "Image URL": "https://i.ebayimg.com/thumbs/images/g/ID8AAOSwUWtkEA8l/s-l225.jpg"
    },
    {
        "Title": "Bright LED light bulbs for a Deere x300 x304 x320 x340 x360 x500 x520 x534 x540",
        "Price": "$19.49",
        "Image URL": "https://i.ebayimg.com/thumbs/images/g/OcgAAOSwa3Rioqz7/s-l225.jpg"
    },
    {
        "Title": "Shop on eBay",
        "Price": "$20.00",
        "Image URL": "https://ir.ebaystatic.com/rs/v/fxxj3ttftm5ltcqnto1o4baovyl.png"
    },
    {
        "Title": "Bright LED light bulbs for a Deere x300 x304 x320 x340 x360 x500 x520 x534 x540",
        "Price": "$19.49",
        "Image URL": "https://i.ebayimg.com/thumbs/images/g/OcgAAOSwa3Rioqz7/s-l225.jpg"
    },
    {
        "Title": "Tow LED Headlight Bulbs Riding Tractor Riding Lawn Mower Snow for 1156 Deere Cub",
        "Price": "$19.94",
        "Image URL": "https://i.ebayimg.com/thumbs/images/g/t4UAAOSwjGBh1UvR/s-l225.jpg"
    },
    {
        "Title": "For Castel Garden 1873611 Magnetic Switch Switch 12V 1873611 Lawn Tractor",
        "Price": "$16.55",
        "Image URL": "https://i.ebayimg.com/thumbs/images/g/x7gAAOSw8fNkPXGp/s-l225.jpg"
    },
    {
        "Title": "3 SUPER LED light bulbs for Deere 655 755 855 955 headlights tractor bulb mower",
        "Price": "$13.26",
        "Image URL": "https://i.ebayimg.com/thumbs/images/g/luIAAOSwRYpjEWI9/s-l225.jpg"
    },
    {
        "Title": "DX SALE 2-   TROY-BILT GARDEN TRACTOR VINYL DECALS ON BLACK",
        "Price": "$7.99",
        "Image URL": "https://i.ebayimg.com/thumbs/images/g/CoQAAMXQBwlRVyVz/s-l225.jpg"
    },
    {
        "Title": "John Deere foot grips for  Models 200,208,210,212,214,216,400  Garden tractor",
        "Price": "$19.50",
        "Image URL": "https://i.ebayimg.com/thumbs/images/g/IngAAOSwX2Bc3z~u/s-l225.jpg"
    },
    {
        "Title": "John Deere LT155 LAWN&GARDEN TRACTOR TRANSMISSON  AM122742",
        "Price": "$150.00",
        "Image URL": "https://i.ebayimg.com/thumbs/images/g/yvsAAOSw265jaYb4/s-l225.jpg"
    },
    {
        "Title": "Wisconsin Engine ID Plate - Brand New! / Antique Vintage Garden Tractor Tag AENL",
        "Price": "$35.00",
        "Image URL": "https://i.ebayimg.com/thumbs/images/g/u1oAAOSwZR9ac6XV/s-l225.jpg"
    },
    {
        "Title": "Electronic Ignition Module Fits John Deere M70114 Lawn Mower Garden Tractor",
        "Price": "$18.94",
        "Image URL": "https://i.ebayimg.com/thumbs/images/g/pywAAOSwTh9kNPoZ/s-l225.jpg"
    },
    {
        "Title": "MTD LAWN & GARDEN TRACTOR WIRING HARNESS",
        "Price": "$44.99",
        "Image URL": "https://i.ebayimg.com/thumbs/images/g/aCwAAOSwRvtimX7N/s-l225.jpg"
    },
    {
        "Title": "(Pack of 3) Spindle Assembly for Exmark Quest & Toro TimeCutter Zero-Turn Mowers",
        "Price": "$69.99",
        "Image URL": "https://i.ebayimg.com/thumbs/images/g/1L0AAOSwUrhi1t12/s-l225.jpg"
    },
    {
        "Title": "4pk Deck Wheel +6 Piece Hardware Kit Fits JD AM133602 AM116299 M111489",
        "Price": "$47.99",
        "Image URL": "https://i.ebayimg.com/thumbs/images/g/i0MAAOSwDsdjoU87/s-l225.jpg"
    },
    {
        "Title": "Mower Deck Secondary Belt for John Deere Lawn and Garden Tractor M162443 M158692",
        "Price": "$11.49",
        "Image URL": "https://i.ebayimg.com/thumbs/images/g/2EsAAOSwIzpdWrfh/s-l225.jpg"
    },
    {
        "Title": "Garden Power Tool Parts Cable Tractor Lawn Lawn Mower Suitable For 169676 175067",
        "Price": "$9.71",
        "Image URL": "https://i.ebayimg.com/thumbs/images/g/cWcAAOSwfUtj6DoB/s-l225.jpg"
    },
    {
        "Title": "Tow LED Headlight Bulbs Riding Tractor Riding Lawn Mower Snow for 1156 Deere Cub",
        "Price": "$15.99",
        "Image URL": "https://i.ebayimg.com/thumbs/images/g/S1UAAOSwkoRi8irc/s-l225.jpg"
    },
    {
        "Title": "LED Headlight Bulb for Riding Lawn Tractor Riding Lawn Mower Snow 1156 Deere Cub",
        "Price": "$16.61",
        "Image URL": "https://i.ebayimg.com/thumbs/images/g/nMYAAOSwKq9g~hmi/s-l225.jpg"
    },
    {
        "Title": "Pair of Chain Tensioners for  20x8x8, 20x10x8, 23x8.5x12 Yard Garden Tractor",
        "Price": "$12.49",
        "Image URL": "https://i.ebayimg.com/thumbs/images/g/KZIAAOSwuNxiFmHc/s-l225.jpg"
    },
    {
        "Title": "JOHN DEERE 425,445,345 F725,LX188  LAWN & GARDEN TRACTOR COIL",
        "Price": "$8.00",
        "Image URL": "https://i.ebayimg.com/thumbs/images/g/uAIAAOSwdudbjFPm/s-l225.jpg"
    },
    {
        "Title": "5 Honda Ride on Lawn Mower Garden Tractor Ignition Key 35111-VL0-W01",
        "Price": "$9.20",
        "Image URL": "https://i.ebayimg.com/thumbs/images/g/tPMAAOSw3Vxj31tu/s-l225.jpg"
    },
    {
        "Title": "Rotary Tire Sealant 32 Oz Lawn & Garden tractors farm atv offroad",
        "Price": "$29.99",
        "Image URL": "https://i.ebayimg.com/thumbs/images/g/O0YAAOSwa6tjSBt8/s-l225.jpg"
    },
    {
        "Title": "John Deere 265 285 320 245 Tractor Brake Rod",
        "Price": "$25.79",
        "Image URL": "https://i.ebayimg.com/thumbs/images/g/JxMAAOSw32BgPCoR/s-l225.jpg"
    },
    {
        "Title": "John Deere(B5-069) 316 - Neutral Return Shaft",
        "Price": "$44.99",
        "Image URL": "https://i.ebayimg.com/thumbs/images/g/cDwAAOSwkj5ivGul/s-l225.jpg"
    },
    {
        "Title": "OIL FILTER fits Kawasaki FB460V FC420V FC540V FD501D FD590V FR651V FR691V FR730V",
        "Price": "$13.99",
        "Image URL": "https://i.ebayimg.com/thumbs/images/g/SZAAAOSweJ1fHubG/s-l225.jpg"
    },
    {
        "Title": "Control Cable for Craftsman 917377423, 917377424, 917377425 & 91737742A Mower",
        "Price": "$9.99",
        "Image URL": "https://i.ebayimg.com/thumbs/images/g/kx0AAOSw4UJgv9nk/s-l225.jpg"
    },
    {
        "Title": "Engine Control Cable for Weed Eater 961140007, 96114000800, 96114001404 Mower",
        "Price": "$8.99",
        "Image URL": "https://i.ebayimg.com/thumbs/images/g/NEgAAOSwqyBiKUGp/s-l225.jpg"
    },
    {
        "Title": "Single Terminal Electronic Ignition Module for John Deere Tractor GT262, GT275",
        "Price": "$18.99",
        "Image URL": "https://i.ebayimg.com/thumbs/images/g/OiQAAOSweWZkEMaR/s-l225.jpg"
    },
    {
        "Title": "2 Blinding Bright LED headlight bulbs for Deere X540 X570 X580 X584 X590 tractor",
        "Price": "$17.99",
        "Image URL": "https://i.ebayimg.com/thumbs/images/g/3IIAAOSwdNFh84B6/s-l225.jpg"
    },
    {
        "Title": "Starter Solenoid for Simplicity 1686981, 1686981SM, 1686981YP & 1686982 4 Post",
        "Price": "$15.49",
        "Image URL": "https://i.ebayimg.com/thumbs/images/g/BQIAAOSwg7BhvN-5/s-l225.jpg"
    },
    {
        "Title": "LED Light Bulb White for Kenmore Sewing Machine 385.18836 385.18841 385.195018",
        "Price": "$17.13",
        "Image URL": "https://i.ebayimg.com/thumbs/images/g/mTkAAOSwUU9hnvAV/s-l225.jpg"
    },
    {
        "Title": "SET Of TWO 15X6X6 15X6.00-6 Turf Tires Garden Tractor Lawn Mower Riding Mower",
        "Price": "$97.99",
        "Image URL": "https://i.ebayimg.com/thumbs/images/g/nBEAAOSwgPNjecWY/s-l225.jpg"
    },
    {
        "Title": "3x White LED light bulbs for Deere 655 755 855 955 headlights tractor bulb mower",
        "Price": "$15.51",
        "Image URL": "https://i.ebayimg.com/thumbs/images/g/pUMAAOSwwC9h6QL8/s-l225.jpg"
    },
    {
        "Title": "Pair 1156 LED Bulbs for Deere 655 755 855 955 Headlight Bulb 6000K",
        "Price": "$17.99",
        "Image URL": "https://i.ebayimg.com/thumbs/images/g/HFUAAOSwS9hjQ8jv/s-l225.jpg"
    },
    {
        "Title": "Fuel Pump & Filter NEW for John Deere Lawn and Garden Tractor X485 X585",
        "Price": "$38.00",
        "Image URL": "https://i.ebayimg.com/thumbs/images/g/IT8AAOSwt5FhwQpb/s-l225.jpg"
    },
    {
        "Title": "Ignition Starter Switch for John Deere 300, 312, 314, 316, 317, 400 Tractor Keys",
        "Price": "$14.99",
        "Image URL": "https://i.ebayimg.com/thumbs/images/g/LpEAAOSw~WJivu2M/s-l225.jpg"
    },
    {
        "Title": "DX SNAPPER GARDEN TRACTOR  VINYL DECALS WHITE",
        "Price": "$6.99",
        "Image URL": "https://i.ebayimg.com/thumbs/images/g/zeAAAOSw-W5UyC5m/s-l225.jpg"
    },
    {
        "Title": "Cub Cadet 3000 Series Mower Deck Spindle 759-3665 959-3665 42\" 46\" 48\" 54\"",
        "Price": "$147.86",
        "Image URL": "https://i.ebayimg.com/thumbs/images/g/FNQAAOSwnC1ihvCA/s-l225.jpg"
    },
    {
        "Title": "LED Headlight Bulb for John Deere G100 GT225 GT235 GT245 GX255 GX335 GX345 GX355",
        "Price": "$9.99",
        "Image URL": "https://i.ebayimg.com/thumbs/images/g/JnEAAOSwXepefGB3/s-l225.jpg"
    },
    {
        "Title": "Deck Engagement Clutch Cable for AYP, Craftsman, Roper 197257, 435111 Lawn Mower",
        "Price": "$14.49",
        "Image URL": "https://i.ebayimg.com/thumbs/images/g/UtsAAOSw8K9kC0ne/s-l225.jpg"
    },
    {
        "Title": "3 SUPER LED light bulbs for Deere 655 755 855 955 headlights tractor bulb mower",
        "Price": "$22.99",
        "Image URL": "https://i.ebayimg.com/thumbs/images/g/xo8AAOSwvuthpuSI/s-l225.jpg"
    },
    {
        "Title": "Cool White LED light bulbs for Troy-Bilt Pony Super Bronco Horse bulb headlights",
        "Price": "$13.99",
        "Image URL": "https://i.ebayimg.com/thumbs/images/g/mAoAAOSwGVJkEA8m/s-l225.jpg"
    },
    {
        "Title": "8x7 3/4\" shaft Drive axle Go Kart Garden Tractor Riding lawn mower RIM WHEEL P10",
        "Price": "$47.76",
        "Image URL": "https://i.ebayimg.com/thumbs/images/g/hLUAAMXQskFRHDT~/s-l225.jpg"
    },
    {
        "Title": "Homelite Footrests, Left & Right  T-16 H Garden Tractor",
        "Price": "$49.99",
        "Image URL": "https://i.ebayimg.com/thumbs/images/g/918AAOSwITxjG~yS/s-l225.jpg"
    },
    {
        "Title": "D=  SIMPLICITY GARDEN TRACTOR BLACK VINYL DECALS  US",
        "Price": "$5.99",
        "Image URL": "https://i.ebayimg.com/thumbs/images/g/rqcAAOSwejdbZbHw/s-l225.jpg"
    },
    {
        "Title": "(2) AYP 3645J Gas Fuel Tank Grommet Lawn Garden Tractor fits Craftsman - NEW",
        "Price": "$13.35",
        "Image URL": "https://i.ebayimg.com/thumbs/images/g/6EkAAOSwuOxZxgeu/s-l225.jpg"
    },
    {
        "Title": "Genuine OEM Grasshopper Fuel Cap Gauge for 1998-2005 Front Mount 928D2 Tractors",
        "Price": "$41.49",
        "Image URL": "https://i.ebayimg.com/thumbs/images/g/MXoAAOSwoCJhujcz/s-l225.jpg"
    },
    {
        "Title": "Garden tractor loader cyl rebuild kits for Johnson 10,10TC,12,14(1.5\" cyl)",
        "Price": "$150.00",
        "Image URL": "https://i.ebayimg.com/thumbs/images/g/GZkAAOSwNb1ivG5A/s-l225.jpg"
    },
    {
        "Title": "Electric PTO Clutch & Wire Harness for Craftsman PGT9000 247289840, 247289841",
        "Price": "$154.99",
        "Image URL": "https://i.ebayimg.com/thumbs/images/g/QOEAAOSwPfRjCNTc/s-l225.jpg"
    },
    {
        "Title": "Cub Cadet Garden Tractor Ross Easy Steering Upgrade Kit For 109,122,123 & 124",
        "Price": "$16.75",
        "Image URL": "https://i.ebayimg.com/thumbs/images/g/O0EAAOSwLYlj1yYu/s-l225.jpg"
    },
    {
        "Title": "Replacement TORO PART # 88-9932 SWITCH FOR TORO LAWN AND GARDEN TRACTORS",
        "Price": "$21.00",
        "Image URL": "https://i.ebayimg.com/thumbs/images/g/RswAAOSwxy9jl8NW/s-l225.jpg"
    },
    {
        "Title": "Engine Control Cable for Craftsman 917378921, 917376080 Walk-Behind Lawnmowers",
        "Price": "$10.49",
        "Image URL": "https://i.ebayimg.com/thumbs/images/g/l2kAAOSw-31iJ3je/s-l225.jpg"
    },
    {
        "Title": "Ariens 931 Series Garden Tractor Factory Dealer Repair Manual",
        "Price": "$19.00",
        "Image URL": "https://i.ebayimg.com/thumbs/images/g/2dgAAOSw~p1kTCB5/s-l225.jpg"
    },
    {
        "Title": "TIRE INNER TUBE 11x4.00x5 12x4.00x5 TR87 90\u00b0 Bent Valve for Toro Mower Tractor",
        "Price": "$12.49",
        "Image URL": "https://i.ebayimg.com/thumbs/images/g/GroAAOSwbtNaPQ-d/s-l225.jpg"
    },
    {
        "Title": "Blade Control Cable for 2004 Troy-Bilt 12A-566N766, 200 & 2010 Tuff-Cut Mower",
        "Price": "$9.49",
        "Image URL": "https://i.ebayimg.com/thumbs/images/g/Ii0AAOSw45xguh5z/s-l225.jpg"
    },
    {
        "Title": "For D100 E100 G100 L100 LT150 X300 X350 tractor JD Deere AD2062R LED Light Bulb",
        "Price": "$11.73",
        "Image URL": "https://i.ebayimg.com/thumbs/images/g/AvAAAOSweHhkHQtZ/s-l225.jpg"
    },
    {
        "Title": "Ariens S series Garden Tractor LH steering spindle",
        "Price": "$6.90",
        "Image URL": "https://i.ebayimg.com/thumbs/images/g/G6cAAOSwYMdjmp0D/s-l225.jpg"
    },
    {
        "Title": "JOHN DEER  LA140     LAWN & GARDEN TRACTOR  TIE RODS",
        "Price": "$12.00",
        "Image URL": "https://i.ebayimg.com/thumbs/images/g/q1wAAOSwvddfpzDX/s-l225.jpg"
    },
    {
        "Title": "Case Ingersoll Ignition Switch C30530 For Lawn Yard Garden Tractor Mower",
        "Price": "$30.36",
        "Image URL": "https://i.ebayimg.com/thumbs/images/g/F28AAOSwvNdi7Bpj/s-l225.jpg"
    },
    {
        "Title": "(Pack of 2) Control Cable for Weed Eater 961140007, 96114000800, 96114001404",
        "Price": "$10.99",
        "Image URL": "https://i.ebayimg.com/thumbs/images/g/nWMAAOSwbyhiKhLC/s-l225.jpg"
    },
    {
        "Title": "Lawn & Garden Tractor Ignition Switch Harness Fits Wheel Horse Gravely Toro MTD",
        "Price": "$11.49",
        "Image URL": "https://i.ebayimg.com/thumbs/images/g/RCQAAOSwEaReiQSf/s-l225.jpg"
    },
    {
        "Title": "Carburetor with Gaskets for John Deere LX178, LX186, LX188 Yard Tractor Engines",
        "Price": "$23.99",
        "Image URL": "https://i.ebayimg.com/thumbs/images/g/Z-4AAOSwSDxefkVA/s-l225.jpg"
    },
    {
        "Title": "John Deere 400 Garden Tractor- Brake Pad M43646",
        "Price": "$14.99",
        "Image URL": "https://i.ebayimg.com/thumbs/images/g/GSUAAOSwe6dg8cuK/s-l225.jpg"
    },
    {
        "Title": "2pcs LED 1156  lawn tractor light bulb for John Deere LA100 LA105 LA110",
        "Price": "$17.99",
        "Image URL": "https://i.ebayimg.com/thumbs/images/g/OI4AAOSwzLdjQ8jw/s-l225.jpg"
    },
    {
        "Title": "LED light bulbs For Craftsman riding mower tractor headlamp bulb Sears 4152j 2x",
        "Price": "$17.99",
        "Image URL": "https://i.ebayimg.com/thumbs/images/g/3YAAAOSwtc5jNpTS/s-l225.jpg"
    },
    {
        "Title": "Simplicity 3112V Tractor Miscellaneous Wiring Clips",
        "Price": "$10.99",
        "Image URL": "https://i.ebayimg.com/thumbs/images/g/t1gAAOSwiFZjnP1H/s-l225.jpg"
    },
    {
        "Title": "2 NEW LAWN 20X10.00-10 TURF TIRE 4 PLY  Mower Garden Tractor 20 10 10",
        "Price": "$110.87",
        "Image URL": "https://i.ebayimg.com/thumbs/images/g/wTYAAOSwDNdVv8F5/s-l225.jpg"
    },
    {
        "Title": "New Ariens GT Garden Tractor Lawn Mower Deck Skid Runner 03034559 03034500",
        "Price": "$37.83",
        "Image URL": "https://i.ebayimg.com/thumbs/images/g/gpIAAOSwMmBV6e6K/s-l225.jpg"
    },
    {
        "Title": "FUEL PUMP fits John Deere D100 D105 D110 D120 D125 D130 D140 D150 D155 Tractors",
        "Price": "$20.49",
        "Image URL": "https://i.ebayimg.com/thumbs/images/g/QjMAAOSw9hdaAwlU/s-l225.jpg"
    },
    {
        "Title": "OEM Simplicity 1715859 1715859SM Foot Pedal Assy for Garden Tractors",
        "Price": "$25.00",
        "Image URL": "https://i.ebayimg.com/thumbs/images/g/gnsAAOSwkaRjuc-a/s-l225.jpg"
    },
    {
        "Title": "Electric PTO Clutch for Hustler Series ATZ, X-One, Z4, Super Z, Z with XR-7 Deck",
        "Price": "$159.99",
        "Image URL": "https://i.ebayimg.com/thumbs/images/g/h2UAAOSwptdjD4Dq/s-l225.jpg"
    },
    {
        "Title": "PTO Cable for John Deere LA100, LA105, LA110, LA115, LA120, LA125 & LA135 Mower",
        "Price": "$13.99",
        "Image URL": "https://i.ebayimg.com/thumbs/images/g/QXAAAOSw-HtkCf5O/s-l225.jpg"
    },
    {
        "Title": "DX 2- WHEEL HORSE GARDEN TRACTOR DECALS RED HUB  1L & 1R",
        "Price": "$6.99",
        "Image URL": "https://i.ebayimg.com/thumbs/images/g/Q-wAAOSwQj9dk3lC/s-l225.jpg"
    },
    {
        "Title": "Carburetor Float Bowl Gasket for Kohler 17 HP KT17-24323 Small Engine Mower",
        "Price": "$7.49",
        "Image URL": "https://i.ebayimg.com/thumbs/images/g/UmIAAOSwqgBgJAKL/s-l225.jpg"
    },
    {
        "Title": "CRAFTSMAN LAWN & GARDEN TRACTOR BRAKE ROD",
        "Price": "$14.99",
        "Image URL": "https://i.ebayimg.com/thumbs/images/g/oUoAAOSwh8djz0sz/s-l225.jpg"
    },
    {
        "Title": "3 light bulbs for a IH Farmall John Deere Allis Oliver Massey 1156 LED 12 V Bulb",
        "Price": "$14.29",
        "Image URL": "https://i.ebayimg.com/thumbs/images/g/~-IAAOSwwythpuSJ/s-l225.jpg"
    },
    {
        "Title": "SUPER Bright LED bulbs For  LTX1040 LTX1042 LTX1045 LTX1050 mower",
        "Price": "$12.98",
        "Image URL": "https://i.ebayimg.com/thumbs/images/g/IrgAAOSw8zdkNhYp/s-l225.jpg"
    }
]